tutorial_package_jiyu/__init__.py
tutorial_package_jiyu/greet.py
tutorial_package_jiyu-0.0.2.dist-info/DESCRIPTION.rst
tutorial_package_jiyu-0.0.2.dist-info/METADATA
tutorial_package_jiyu-0.0.2.dist-info/RECORD
tutorial_package_jiyu-0.0.2.dist-info/WHEEL
tutorial_package_jiyu-0.0.2.dist-info/metadata.json
tutorial_package_jiyu-0.0.2.dist-info/top_level.txt
