Metadata-Version: 2.0
Name: tutorial-package-jiyu
Version: 0.0.2
Summary: An demonstration of how to create and publish python packages
Home-page: UNKNOWN
Author: Uwe Schmitt
Author-email: UNKNOWN
License: BSD
Platform: UNKNOWN
Requires-Dist: big-letters
